mergechannels/__init__.py
mergechannels/_blending.py
mergechannels/_internal.py
mergechannels/_luts.py
mergechannels/mergechannels.cpython-313-s390x-linux-gnu.so
mergechannels/py.typed
mergechannels-0.6.1.dist-info/METADATA
mergechannels-0.6.1.dist-info/WHEEL
mergechannels-0.6.1.dist-info/licenses/LICENSE
mergechannels-0.6.1.dist-info/RECORD
