Metadata-Version: 2.4
Name: mergechannels
Version: 0.6.1
Classifier: License :: OSI Approved :: MIT License
Classifier: Framework :: Matplotlib
Classifier: Programming Language :: Rust
Classifier: Programming Language :: Python :: Implementation :: CPython
Classifier: Programming Language :: Python :: 3
Classifier: Programming Language :: Python :: 3.9
Classifier: Programming Language :: Python :: 3.10
Classifier: Programming Language :: Python :: 3.11
Classifier: Programming Language :: Python :: 3.12
Classifier: Programming Language :: Python :: 3.13
Classifier: Programming Language :: Python :: 3.14
Classifier: Programming Language :: Python :: Free Threading
Requires-Dist: numpy>=1.25,<2.1 ; python_full_version == '3.9.*'
Requires-Dist: numpy>=1.25,<2.3 ; python_full_version == '3.10.*'
Requires-Dist: numpy>=1.25,<3 ; python_full_version == '3.11.*'
Requires-Dist: numpy>=1.26,<3 ; python_full_version == '3.12.*'
Requires-Dist: numpy>=2.0,<3 ; python_full_version == '3.13.*'
Requires-Dist: numpy>=2.4,<3 ; python_full_version == '3.14.*'
Requires-Dist: matplotlib>=3.5 ; extra == 'matplotlib'
Provides-Extra: matplotlib
License-File: LICENSE
Summary: Apply and merge colormaps
Author-email: Zac Swider <zac.swider@gmail.com>
License: MIT
Requires-Python: >=3.9, <3.15
